CHANGES.txt
LICENSE.txt
MANIFEST.in
README.txt
setup.py
airsea/__init__.py
airsea/atmosphere.py
airsea/constants.py
airsea/relhum.py
airsea/windstress.py
airsea.egg-info/PKG-INFO
airsea.egg-info/SOURCES.txt
airsea.egg-info/dependency_links.txt
airsea.egg-info/requires.txt
airsea.egg-info/top_level.txt