Metadata-Version: 1.1
Name: airsea
Version: 0.0.1
Summary: AirSea Libray for Python
Home-page: http://pypi.python.org/pypi/airsea/
Author: Filipe Fernandes
Author-email: ocefpaf@gmail.com
License: The MIT License (MIT)
